gendeblur/__init__.py
gendeblur/gen/__init__.py
gendeblur/gen/crossoverOperators.py
gendeblur/gen/genDeblurrer.py
gendeblur/gen/individual.py
gendeblur/gen/mutationOperators.py
gendeblur/gen/population.py
gendeblur/gen/selectionOperators.py
gendeblur/utils/__init__.py
gendeblur/utils/drawing.py
gendeblur/utils/imgDeconv.py
gendeblur/utils/imgMetrics.py
gendeblur/utils/imgUtils.py
gendeblur/utils/scalePyramid.py
gendeblur-0.0.1.dist-info/LICENSE.md
gendeblur-0.0.1.dist-info/METADATA
gendeblur-0.0.1.dist-info/WHEEL
gendeblur-0.0.1.dist-info/top_level.txt
gendeblur-0.0.1.dist-info/RECORD
