Metadata-Version: 2.1
Name: gendeblur
Version: 0.0.1
Summary: Library for blind image deconvolution using genetic algorithm
Home-page: https://github.com/EpigramxD/GenDeblur
Author: Medvedkov Nikita
Author-email: nikitakruspe@gmail.com
Project-URL: Bug Tracker, https://github.com/EpigramxD/GenDeblur/issues
Classifier: Programming Language :: Python :: 3
Classifier: License :: OSI Approved :: MIT License
Classifier: Operating System :: OS Independent
Requires-Python: >=3.7
License-File: LICENSE.md
Requires-Dist: tifffile (==2021.4.8)
Requires-Dist: six (==1.16.0)
Requires-Dist: setuptools (==41.2.0)
Requires-Dist: scipy (==1.6.3)
Requires-Dist: scikit-image (==0.18.2)
Requires-Dist: PyWavelets (==1.1.1)
Requires-Dist: python-dateutil (==2.8.2)
Requires-Dist: pyparsing (==2.4.7)
Requires-Dist: Pillow (==8.3.1)
Requires-Dist: opencv-python
Requires-Dist: opencv-contrib-python (==4.5.3.56)
Requires-Dist: numpy (==1.21.1)
Requires-Dist: networkx (==2.6.2)
Requires-Dist: matplotlib (==3.4.2)
Requires-Dist: libsvm (==3.23.0.4)
Requires-Dist: kiwisolver (==1.3.1)
Requires-Dist: imageio (==2.9.0)
Requires-Dist: image-quality (==1.2.7)
Requires-Dist: cycler (==0.10.0)
Requires-Dist: cpbd (==1.0.7)
Requires-Dist: pyyaml (==6.0)
